{
    "is_weighted": true,
    "size": 3,
    "edges": [
        {
            "from": 2,
            "to": 2,
            "weight": 1
        },
        {
            "from": 1,
            "to": 2,
            "weight": 3
        },
        {
            "from": 2,
            "to": 3,
            "weight": 2
        },
        {
            "from": 3,
            "to": 1,
            "weight": 4
        },
        {
            "from": 4,
            "to": 1,
            "weight": 4
        },
        {
            "from": 4,
            "to": 2,
            "weight": 2
        },
        {
            "from": 4,
            "to": 3,
            "weight": 1
        },
        {
            "from": 4,
            "to": 4,
            "weight": 8
        }
    ],
    "nodes": [
        {
            "code": 1,
            "name": "joao",
            "local_type": "pedro"
        },
        {
            "code": 2,
            "name": "alo",
            "local_type": "teste"
        },
        {
            "code": 3,
            "name": "vertice",
            "local_type": "tres"
        },
        
        {
            "code": 4,
            "name": "alo teste",
            "local_type": "oi"
        }
    ]
}
